{
  "paths": [
    {
      "from": "Medewerker inkoopadministratie-fwg40",
      "to": "Gegevensbeheerder-fwg50",
      "timeframe": ""
    },
    {
      "from": "Gegevensbeheerder-fwg50",
      "to": "Junior Inkoper-fwg50",
      "timeframe": ""
    },
    {
      "from": "Junior Inkoper-fwg50",
      "to": "Assortimentsspecialist-fwg55",
      "timeframe": ""
    },
    {
      "from": "Junior Inkoper-fwg50",
      "to": "Inkoper-fwg60",
      "timeframe": ""
    },
    {
      "from": "Inkoper-fwg60",
      "to": "Beleidsadviseur-fwg60",
      "timeframe": ""
    },
    {
      "from": "Inkoper-fwg60",
      "to": "Teamleider-fwg60",
      "timeframe": ""
    },
    {
      "from": "Inkoper-fwg60",
      "to": "Contractmanager-fwg60",
      "timeframe": ""
    },
    {
      "from": "Contractmanager-fwg60",
      "to": "Inkoper-fwg60",
      "timeframe": ""
    },
    {
      "from": "Contractmanager-fwg60",
      "to": "Teamleider-fwg60",
      "timeframe": ""
    },
    {
      "from": "Contractmanager-fwg60",
      "to": "Beleidsadviseur-fwg60",
      "timeframe": ""
    },
    {
      "from": "Beleidsadviseur-fwg60",
      "to": "Contractmanager-fwg60",
      "timeframe": ""
    },
    {
      "from": "Beleidsadviseur-fwg60",
      "to": "Teamleider-fwg60",
      "timeframe": ""
    },
    {
      "from": "Beleidsadviseur-fwg60",
      "to": "Inkoper-fwg60",
      "timeframe": ""
    },
    {
      "from": "Teamleider-fwg60",
      "to": "Inkoper-fwg60",
      "timeframe": ""
    },
    {
      "from": "Teamleider-fwg60",
      "to": "Beleidsadviseur-fwg60",
      "timeframe": ""
    },
    {
      "from": "Teamleider-fwg60",
      "to": "Contractmanager-fwg60",
      "timeframe": ""
    },
    {
      "from": "Assortimentsspecialist-fwg55",
      "to": "Inkoper-fwg60",
      "timeframe": ""
    },
    {
      "from": "Assortimentsspecialist-fwg55",
      "to": "Contractmanager-fwg60",
      "timeframe": ""
    },
    {
      "from": "Assortimentsspecialist-fwg55",
      "to": "Teamleider-fwg60",
      "timeframe": ""
    },
    {
      "from": "Logistiek medewerker E-fwg20",
      "to": "Logistiek medewerker D-fwg25",
      "timeframe": ""
    },
    {
      "from": "Logistiek medewerker E-fwg20",
      "to": "chauffeur-fwg25",
      "timeframe": ""
    },
    {
      "from": "Logistiek medewerker E-fwg20",
      "to": "coordinator meewerkend schoonmaak-fwg25",
      "timeframe": "Is dit logisch?"
    },
    {
      "from": "medewerker afdelingslogistiek-fwg20",
      "to": "Logistiek medewerker E-fwg20",
      "timeframe": ""
    },
    {
      "from": "medewerker afdelingslogistiek-fwg20",
      "to": "coordinator meewerkend schoonmaak-fwg25",
      "timeframe": "Is dit logisch?"
    },
    {
      "from": "Logistiek medewerker D-fwg25",
      "to": "chauffeur-fwg25",
      "timeframe": ""
    },
    {
      "from": "Logistiek medewerker D-fwg25",
      "to": "Logistiek medewerker C1-fwg30",
      "timeframe": ""
    },
    {
      "from": "Logistiek medewerker D-fwg25",
      "to": "coordinator meewerkend schoonmaak-fwg25",
      "timeframe": "Is dit logisch?"
    },
    {
      "from": "Logistiek medewerker C1-fwg30",
      "to": "coordinator logistiek-fwg35",
      "timeframe": ""
    },
    {
      "from": "Logistiek medewerker C1-fwg30",
      "to": "coordinator schoonmaak-fwg35",
      "timeframe": ""
    },
    {
      "from": "medewerker Post/Reprografie-fwg25",
      "to": "Logistiek medewerker D-fwg25",
      "timeframe": ""
    },
    {
      "from": "medewerker Post/Reprografie-fwg25",
      "to": "chauffeur-fwg25",
      "timeframe": ""
    },
    {
      "from": "medewerker Post/Reprografie-fwg25",
      "to": "Logistiek medewerker C1-fwg30",
      "timeframe": ""
    },
    {
      "from": "coordinator logistiek-fwg35",
      "to": "Teamleider-fwg50",
      "timeframe": "mits HBO"
    },
    {
      "from": "Teamleider-fwg50",
      "to": "Teamleider-fwg55",
      "timeframe": "mits HBO"
    },
    {
      "from": "Teamleider-fwg55",
      "to": "Teamleider-fwg60",
      "timeframe": "mits HBO en ervaring inkoop"
    },
    {
      "from": "coordinator logistiek-fwg35",
      "to": "Medewerker Receptie & Registratie-fwg35",
      "timeframe": ""
    },
    {
      "from": "chauffeur-fwg25",
      "to": "Logistiek medewerker D-fwg25",
      "timeframe": ""
    },
    {
      "from": "chauffeur-fwg25",
      "to": "medewerker Post/Reprografie-fwg25",
      "timeframe": ""
    },
    {
      "from": "chauffeur-fwg25",
      "to": "Logistiek medewerker C1-fwg30",
      "timeframe": ""
    },
    {
      "from": "Medewerker Receptie & Registratie-fwg35",
      "to": "Medewerker inkoopadministratie-fwg40",
      "timeframe": ""
    },
    {
      "from": "Medewerker Receptie & Registratie-fwg35",
      "to": "Coordinator vrijwilligerswerk-fwg45",
      "timeframe": ""
    },
    {
      "from": "Coordinator vrijwilligerswerk-fwg45",
      "to": "Teamleider-fwg50",
      "timeframe": "mits HBO"
    },
    {
      "from": "Teamleider Receptie & Registratie en Vrijwilligerwerk-fwg55",
      "to": "hoofd veiligheid en ontvangst-fwg65",
      "timeframe": "mits HBO"
    },
    {
      "from": "medewerker beveiliging en bewaking-fwg35",
      "to": "coordinator beveiliging en bewaking-fwg40",
      "timeframe": ""
    },
    {
      "from": "coordinator beveiliging en bewaking-fwg40",
      "to": "teamleider beveiliging en bewaking-fwg55",
      "timeframe": ""
    },
    {
      "from": "teamleider beveiliging en bewaking-fwg55",
      "to": "hoofd veiligheid en ontvangst-fwg65",
      "timeframe": "mits HBO"
    },
    {
      "from": "teamleider beveiliging en bewaking-fwg55",
      "to": "Teamleider Receptie & Registratie en Vrijwilligerwerk-fwg55",
      "timeframe": ""
    },
    {
      "from": "medewerker beveiliging en bewaking-fwg35",
      "to": "Medewerker Receptie & Registratie-fwg35",
      "timeframe": ""
    },
    {
      "from": "coordinator beveiliging en bewaking-fwg40",
      "to": "Coordinator vrijwilligerswerk-fwg45",
      "timeframe": ""
    },
    {
      "from": "keukenassistent-fwg15",
      "to": "assistent kok-fwg25",
      "timeframe": "Mits opleiding"
    },
    {
      "from": "assistent kok-fwg25",
      "to": "2e kok-fwg35",
      "timeframe": "Mits opleiding"
    },
    {
      "from": "assistent kok-fwg25",
      "to": "senior facilitair medewerker-fwg30",
      "timeframe": ""
    },
    {
      "from": "assistent kok-fwg25",
      "to": "voedingsadministratie-fwg40",
      "timeframe": ""
    },
    {
      "from": "2e kok-fwg35",
      "to": "1e kok + add coordinator -fwg40",
      "timeframe": ""
    },
    {
      "from": "2e kok-fwg35",
      "to": "voedingsadministratie-fwg40",
      "timeframe": ""
    },
    {
      "from": "1e kok + add coordinator -fwg40",
      "to": "teamleider patiëntenvoeding-fwg55",
      "timeframe": "Mits opleiding"
    },
    {
      "from": "1e kok + add coordinator -fwg40",
      "to": "Teamleider horeca-fwg50",
      "timeframe": "Mits opleiding"
    },
    {
      "from": "voedingsadministratie-fwg40",
      "to": "teamleider patiëntenvoeding-fwg55",
      "timeframe": "Mits opleiding"
    },
    {
      "from": "teamleider patiëntenvoeding-fwg55",
      "to": "hoofd hospitality-fwg75",
      "timeframe": "Mits opleiding"
    },
    {
      "from": "senior facilitair medewerker-fwg30",
      "to": "Coördinator catering-fwg35",
      "timeframe": ""
    },
    {
      "from": "medewerker algemene schoonmaak-fwg15",
      "to": "medewerker specialistische schoonmaak-fwg20",
      "timeframe": ""
    },
    {
      "from": "medewerker algemene schoonmaak-fwg15",
      "to": "medewerker linnenvoorziening-FWG20",
      "timeframe": ""
    },
    {
      "from": "medewerker linnenvoorziening-FWG20",
      "to": "coordinator meewerkend schoonmaak-fwg25",
      "timeframe": ""
    },
    {
      "from": "medewerker specialistische schoonmaak-fwg20",
      "to": "coordinator meewerkend schoonmaak-fwg25",
      "timeframe": "mits ervaring"
    },
    {
      "from": "coordinator meewerkend schoonmaak-fwg25",
      "to": "coordinator schoonmaak-fwg35",
      "timeframe": "mits ervaring"
    },
    {
      "from": "coordinator schoonmaak-fwg35",
      "to": "Operationeel teamleider schoonmaak-fwg45",
      "timeframe": "mits ervaring"
    },
    {
      "from": "Logistiek medewerker E-fwg20",
      "to": "zorgassistent-fwg30",
      "timeframe": ""
    },
    {
      "from": "medewerker afdelingslogistiek-fwg20",
      "to": "zorgassistent-fwg30",
      "timeframe": ""
    },
    {
      "from": "Logistiek medewerker D-fwg25",
      "to": "zorgassistent-fwg30",
      "timeframe": ""
    },
    {
      "from": "medewerker Post/Reprografie-fwg25",
      "to": "zorgassistent-fwg30",
      "timeframe": ""
    },
    {
      "from": "Medewerker restauratieve voorzieningen-fwg20",
      "to": "Medewerker fsp-fwg35",
      "timeframe": ""
    },
    {
      "from": "Medewerker restauratieve voorzieningen-fwg20",
      "to": "Medewerker vergaderservice-fwg20",
      "timeframe": ""
    },
    {
      "from": "Medewerker restauratieve voorzieningen-fwg20",
      "to": "Medewerker vergaderservice-fwg25",
      "timeframe": ""
    },
    {
      "from": "Medewerker restauratieve voorzieningen-fwg20",
      "to": "Medewerker koffievoorzieningen-fwg20",
      "timeframe": ""
    },
    {
      "from": "Medewerker restauratieve voorzieningen-fwg20",
      "to": "Coördinator catering-fwg35",
      "timeframe": ""
    },
    {
      "from": "Medewerker restauratieve voorzieningen-fwg20",
      "to": "zorgassistent-fwg30",
      "timeframe": ""
    },
    {
      "from": "Medewerker restauratieve voorzieningen-fwg20",
      "to": "Medewerker Receptie & Registratie-fwg35",
      "timeframe": ""
    },
    {
      "from": "Keuken assistent-fwg15",
      "to": "Medewerker restauratieve voorzieningen-fwg20",
      "timeframe": ""
    },
    {
      "from": "Keuken assistent-fwg15",
      "to": "Logistiek medewerker E-fwg20",
      "timeframe": ""
    },
    {
      "from": "Keuken assistent-fwg15",
      "to": "medewerker specialistische schoonmaak-fwg20",
      "timeframe": ""
    },
    {
      "from": "Keuken assistent-fwg15",
      "to": "Logistiek medewerker D-fwg25",
      "timeframe": ""
    },
    {
      "from": "Leerlingkok",
      "to": "Assistentkok-fwg25",
      "timeframe": ""
    },
    {
      "from": "Leerlingkok",
      "to": "Medewerker restauratieve voorzieningen-fwg20",
      "timeframe": ""
    },
    {
      "from": "Leerlingkok",
      "to": "Logistiek medewerker E-fwg20",
      "timeframe": ""
    },
    {
      "from": "Restaurantkok-fwg30",
      "to": "1e restarantkok-fwg40",
      "timeframe": ""
    },
    {
      "from": "Restaurantkok-fwg30",
      "to": "2e kok-fwg35",
      "timeframe": "Mits opleiding"
    },
    {
      "from": "Restaurantkok-fwg30",
      "to": "voedingsadministratie-fwg40",
      "timeframe": ""
    },
    {
      "from": "1e restarantkok-fwg40",
      "to": "teamleider patiëntenvoeding-fwg55",
      "timeframe": "Mits opleiding"
    },
    {
      "from": "1e restarantkok-fwg40",
      "to": "Teamleider horeca-fwg50",
      "timeframe": "Mits opleiding"
    },
    {
      "from": "1e restarantkok-fwg40",
      "to": "voedingsadministratie-fwg40",
      "timeframe": ""
    },
    {
      "from": "Medewerker vergaderservice-fwg20",
      "to": "Medewerker vergaderservice-fwg25",
      "timeframe": ""
    },
    {
      "from": "Medewerker vergaderservice-fwg25",
      "to": "Medewerker fsp-fwg35",
      "timeframe": ""
    },
    {
      "from": "Medewerker koffievoorzieningen-fwg20",
      "to": "Medewerker vergaderservice-fwg25",
      "timeframe": ""
    },
    {
      "from": "Coördinator catering-fwg35",
      "to": "voedingsadministratie-fwg40",
      "timeframe": ""
    },
    {
      "from": "Coördinator catering-fwg35",
      "to": "Teamleider horeca-fwg50",
      "timeframe": ""
    },
    {
      "from": "Coördinator catering-fwg35",
      "to": "teamleider patiëntenvoeding-fwg55",
      "timeframe": ""
    },
    {
      "from": "Teamleider horeca-fwg50",
      "to": "teamleider patiëntenvoeding-fwg55",
      "timeframe": ""
    },
    {
      "from": "Medewerker fsp-fwg35",
      "to": "Medewerker Receptie & Registratie-fwg35",
      "timeframe": ""
    },
    {
      "from": "Medewerker fsp-fwg35",
      "to": "voedingsadministratie-fwg40",
      "timeframe": ""
    },
    {
      "from": "Stafmedewerker-fwg45",
      "to": "Beleidsadviseur-fwg55",
      "timeframe": ""
    },
    {
      "from": "Beleidsadviseur-fwg55",
      "to": "Beleidsadviseur-fwg60",
      "timeframe": ""
    },
    {
      "from": "Teamleider-fwg55",
      "to": "Beleidsadviseur-fwg55",
      "timeframe": ""
    },
    {
      "from": "Teamleider-fwg55",
      "to": "Beleidsadviseur-fwg60",
      "timeframe": ""
    },
    {
      "from": "Beleidsadviseur-fwg55",
      "to": "Teamleider-fwg55",
      "timeframe": ""
    }
  ]
}